CHANGES.rst
DESCRIPTION.rst
LICENSE
MANIFEST.in
README.md
setup.py
src/idc/class_lister.py
src/idc/core.py
src/idc/help.py
src/idc/registry.py
src/idc/api/__init__.py
src/idc/api/_colors.py
src/idc/api/_data.py
src/idc/api/_data_types.py
src/idc/api/_depth.py
src/idc/api/_device.py
src/idc/api/_filter.py
src/idc/api/_fonts.py
src/idc/api/_generator.py
src/idc/api/_geometry.py
src/idc/api/_imgcls.py
src/idc/api/_imgseg.py
src/idc/api/_objdet.py
src/idc/api/_reader.py
src/idc/api/_utils.py
src/idc/api/_writer.py
src/idc/filter/__init__.py
src/idc/filter/_any_to_rgb.py
src/idc/filter/_apply_ext_mask.py
src/idc/filter/_check_duplicate_filenames.py
src/idc/filter/_convert_image_format.py
src/idc/filter/_discard_by_name.py
src/idc/filter/_discard_invalid_images.py
src/idc/filter/_discard_negatives.py
src/idc/filter/_filter_labels.py
src/idc/filter/_grayscale_to_binary.py
src/idc/filter/_inspect.py
src/idc/filter/_label_to_metadata.py
src/idc/filter/_map_labels.py
src/idc/filter/_max_records.py
src/idc/filter/_metadata.py
src/idc/filter/_metadata_from_name.py
src/idc/filter/_metadata_objdet.py
src/idc/filter/_metadata_to_placeholder.py
src/idc/filter/_od_to_ic.py
src/idc/filter/_od_to_is.py
src/idc/filter/_passthrough.py
src/idc/filter/_pyfunc_filter.py
src/idc/filter/_randomize_records.py
src/idc/filter/_record_window.py
src/idc/filter/_remove_classes.py
src/idc/filter/_rename.py
src/idc/filter/_rgb_to_grayscale.py
src/idc/filter/_sample.py
src/idc/filter/_set_placeholder.py
src/idc/filter/_sort_pixels.py
src/idc/filter/_split_records.py
src/idc/filter/_strip_annotations.py
src/idc/filter/_tee.py
src/idc/filter/_use_mask.py
src/idc/filter/_write_labels.py
src/idc/filter/depth/__init__.py
src/idc/filter/depth/_depth_to_grayscale.py
src/idc/filter/imgcls/__init__.py
src/idc/filter/imgcls/_label_from_name.py
src/idc/filter/imgcls/_label_present.py
src/idc/filter/imgseg/__init__.py
src/idc/filter/imgseg/_apply_label_mask.py
src/idc/filter/imgseg/_label_present.py
src/image_dataset_converter.egg-info/PKG-INFO
src/image_dataset_converter.egg-info/SOURCES.txt
src/image_dataset_converter.egg-info/dependency_links.txt
src/image_dataset_converter.egg-info/entry_points.txt
src/image_dataset_converter.egg-info/requires.txt
src/image_dataset_converter.egg-info/top_level.txt