Metadata-Version: 2.1
Name: image-dataset-converter
Version: 0.0.12
Summary: Python3 library for converting between various image annotation dataset formats.
Home-page: https://github.com/waikato-datamining/image-dataset-converter
Author: Peter Reutemann
Author-email: fracpete@waikato.ac.nz
License: MIT License
Classifier: Development Status :: 4 - Beta
Classifier: License :: OSI Approved :: MIT License
Classifier: Topic :: Scientific/Engineering :: Artificial Intelligence
Classifier: Topic :: Scientific/Engineering :: Image Processing
License-File: LICENSE
